miband2/__init__.py
miband2/authsession.py
miband2/band2.py
miband2-0.1.1.dist-info/LICENSE
miband2-0.1.1.dist-info/WHEEL
miband2-0.1.1.dist-info/METADATA
miband2-0.1.1.dist-info/RECORD
